pyswitch/AbstractDevice.py
pyswitch/NetConfDevice.py
pyswitch/RestDevice.py
pyswitch/XMLAsset.py
pyswitch/__init__.py
pyswitch/device.py
pyswitch/exceptions.py
pyswitch/services.py
pyswitch/utilities.py
pyswitch/os/__init__.py
pyswitch/os/base/__init__.py
pyswitch/os/base/bgp.py
pyswitch/os/base/fabric_service.py
pyswitch/os/base/interface.py
pyswitch/os/base/lldp.py
pyswitch/os/base/services.py
pyswitch/os/base/snmp.py
pyswitch/os/base/system.py
pyswitch/os/base/vcs.py
pyswitch/os/nos/__init__.py
pyswitch/os/nos/base/__init__.py
pyswitch/os/nos/base/bgp.py
pyswitch/os/nos/base/interface.py
pyswitch/os/nos/base/services.py
pyswitch/os/nos/base/system.py
pyswitch/os/nos/ver_7/__init__.py
pyswitch/os/nos/ver_7/ver_7_1_0/__init__.py
pyswitch/os/slxos/__init__.py
pyswitch/os/slxos/base/__init__.py
pyswitch/os/slxos/base/bgp.py
pyswitch/os/slxos/base/interface.py
pyswitch/os/slxos/base/isis.py
pyswitch/os/slxos/base/mpls.py
pyswitch/os/slxos/base/ospf.py
pyswitch/os/slxos/base/services.py
pyswitch/os/slxos/base/system.py
pyswitch/raw/__init__.py
pyswitch/raw/base/__init__.py
pyswitch/raw/base/interface.py
pyswitch/raw/nos/__init__.py
pyswitch/raw/nos/base/__init__.py
pyswitch/raw/nos/base/interface.py
pyswitch/raw/nos/base/template.py
pyswitch/raw/slxos/__init__.py
pyswitch/raw/slxos/base/__init__.py
pyswitch/raw/slxos/base/interface.py
pyswitch/raw/slxos/base/template.py
pyswitchlib/__init__.py
pyswitchlib/asset.py
pyswitchlib/exceptions.py
pyswitchlib/api/__init__.py
pyswitchlib/api/create.py
pyswitchlib/api/delete.py
pyswitchlib/api/get.py
pyswitchlib/api/rpc.py
pyswitchlib/api/update.py
pyswitchlib-0.1.82.dist-info/DESCRIPTION.rst
pyswitchlib-0.1.82.dist-info/METADATA
pyswitchlib-0.1.82.dist-info/RECORD
pyswitchlib-0.1.82.dist-info/WHEEL
pyswitchlib-0.1.82.dist-info/metadata.json
pyswitchlib-0.1.82.dist-info/top_level.txt
tests/__init__.py
tests/test_discover/__init__.py
tests/test_discover/test_discover.py
tests/test_pyswitch/__init__.py
tests/test_pyswitch/fail.py
tests/test_pyswitch/test_bgp.py
tests/test_pyswitch/test_device.py
tests/test_pyswitch/test_fabric_service.py
tests/test_pyswitch/test_interface.py
