Metadata-Version: 2.0
Name: pyswitchlib
Version: 0.1.82
Summary: pySwitchLib Library for Brocade switches (SLXOS/NOS)
Home-page: https://github.com/StackStorm/PySwitchLib
Author: Brocade Communications Inc
Author-email: UNKNOWN
License: UNKNOWN
Platform: UNKNOWN
Classifier: Topic :: Utilities
Classifier: Programming Language :: Python
Classifier: Programming Language :: Python :: 2
Classifier: Programming Language :: Python :: 2.7
Classifier: Operating System :: POSIX :: Linux
Classifier: Operating System :: MacOS
Requires-Dist: dicttoxml
Requires-Dist: ipaddress (==1.0.14)
Requires-Dist: jsonpath-rw
Requires-Dist: ncclient (==0.5.3)
Requires-Dist: pyangbind-brcd (>=0.6.14)
Requires-Dist: pybind (>=0.1.27)
Requires-Dist: requests
Requires-Dist: xmltodict
